Workbook
Name SUP: #REF!
Name SUP: #REF!
Name SUP: #REF!

Sheet Logistic
B1: Weight (Kg) | C1: From | D1: To | E1: MOT | F1: Forwarder | G1: FREIGHT | H1: Freight/kg | I1: Transit time
A2: Shipment 1 | B2: 40 | G2: 1800 | H2: =G2/B2 -> 45
A3: Shipment 2
A4: Shipment 3
A5: Shipment 4
A6: Total

Sheet Bank Fee
B2: FORMULA TO CALCULATE BANK FEE
C3: MBBANK
I5: Min | K5: Rate | L5: Amount | M5: Fee
A6: 1 | B6: International remittance | C6: =( 0.2%* amount transfer)*1.1 | I6: 50 | K6: =0.2%*1.1 -> 0.0022 | L6: ='Margin Analysic'!$N$7 -> 3165 | M6: =IF('Margin Analysic'!B4="Local",0,IF(K6*L6>I6,K6*L6,I6)) -> 50
A7: 2 | B7: International Receive | C7: (0.05%* amount transfer) | I7: 35 | K7: =0.005% -> 5e-05 | L7: ='Margin Analysic'!$G$15 -> 3930 | M7: =IF('Margin Analysic'!B3="VN",0,IF(K7*L7>I7,K7*L7,I7)) -> 35
B9: TOTAL FEE | C9: (1)+(2) | M9: =SUM(M6:M8) -> 85
B15: Example: | D15: Transfer: | K15: 662
B18: Bank transfer | C18: 0.002 | D18: x | E18: =+K15 -> 662 | F18: x | G18: 1.1 | H18: = | I18: =+C18*E18*G18 -> 1.4564 | J18: => | K18: =IF((0.2%*$K$15)*1.1>11,(0.2%*$K$15)*1.1,11) -> 11
B19: Bank remittance | K19: =+C7 -> (0.05%* amount transfer)
B20: Bank intl transfer fee | K20: =+$C$8 -> 0
B21: TOTAL bank fee | K21: =SUM(K18:K20) -> 11

Sheet Guide

Sheet Margin Analysic
A1: Job No. | B1: AC0481-DRT-OTHMY | E1: INQ DATE | G1: 46218 | K1: CURRENCY: | L1: USD
A2: Customer: | B2: Baker Huges | E2: Credit (days) | H2: PAYMENT WITH ORDER | K2: USD->EUR: | L2: 1.1
A3: COUNTRY: | B3: MY | E3: Incoterm | H3: FCA | I3: LOUSIANA, US | K3: USD-->VND | L3: 25500
A4: Goods origin | B4: Oversea | H4: DDP | I4: Labuan | M4: Cost
A5: ITEM | B5: Part No. | C5: Description. | D5: Supplier | E5: Q'ty | F5: Weight (kg) | G5: Sales Price | H5: Total Revenue | I5: Margin per unit | J5: % Margin | K5: Total Margin | L5: Total Cost | M5: Unit Cost | N5: Material Cost | O5: Financial Cost
A6: 1 | B6: 480131200 | C6: 1R MODEL F STD. SERVICE DRILL PIPE FLOAT VALVE | D6: KEYSTONE | E6: 30 | F6: =(43.2/E6)*0.46 -> 0.6624 | G6: =ROUNDUP(M6/(1-J6),0) -> 131 | H6: =E6*G6 -> 3930 | I6: =G6-M6 -> 22.666667 | J6: 0.17 | K6: =E6*I6 -> 680 | L6: =M6*E6 -> 3250 | M6: =SUM(N6:O6) -> 108.33333 | N6: 105.5 | O6: =85*(N6/$N$7) -> 2.8333333
E7: =SUM(E6:E6) -> 30 | F7: =SUMPRODUCT($E$6:$E$6,F6:F6) -> 19.872 | G7: =SUMPRODUCT($E$6:$E$6,G6:G6) -> 3930 | H7: =SUM(H6:H6) -> 3930 | I7: =SUMPRODUCT($E$6:$E$6,I6:I6) -> 680 | J7: =AVERAGE(J6:J6) -> 0.17 | K7: =SUM(K6:K6) -> 680 | L7: =SUM(L6:L6) -> 3250 | M7: =SUMPRODUCT($E$6:$E$6,M6:M6) -> 3250 | N7: =SUMPRODUCT($E$6:$E$6,N6:N6) -> 3165 | O7: =SUMPRODUCT($E$6:$E$6,O6:O6) -> 85
A8: ***Please insert row before this line
F10: =F7/0.46 -> 43.2
B12: DAP Kemaman, Malaysia
A13: ITEM | B13: Part No. | C13: Description. | D13: Supplier | E13: Q'ty | F13: Weight (kg) | G13: Sales Price | H13: Total Revenue | I13: Margin per unit | J13: % Margin | K13: Total Margin | L13: Total Cost | M13: Unit Cost | N13: Material Cost | O13: Financial Cost | P13: Frieght
A14: 1 | B14: 480131200 | C14: 1R MODEL F STD. SERVICE DRILL PIPE FLOAT VALVE | D14: KEYSTONE | E14: 30 | F14: =(43.2/E14)*0.46 -> 0.6624 | G14: =ROUNDUP(M14/(1-J14),0) -> 131 | H14: =E14*G14 -> 3930 | I14: =G14-M14 -> 22.666667 | J14: 0.17 | K14: =E14*I14 -> 680 | L14: =M14*E14 -> 3250 | M14: =SUM(N14:O14) -> 108.33333 | N14: 105.5 | O14: =85*(N14/$N$15) -> 2.8333333 | P14: =(Logistic!G2*('Margin Analysic'!F14/'Margin Analysic'!F15)) -> 60
E15: =SUM(E14:E14) -> 30 | F15: =SUMPRODUCT($E$14:$E$14,F14:F14) -> 19.872 | G15: =SUMPRODUCT($E$6:$E$6,G14:G14) -> 3930 | H15: =SUM(H14:H14) -> 3930 | I15: =SUMPRODUCT($E$6:$E$6,I14:I14) -> 680 | J15: =AVERAGE(J14:J14) -> 0.17 | K15: =SUM(K14:K14) -> 680 | L15: =SUM(L14:L14) -> 3250 | M15: =SUMPRODUCT($E$6:$E$6,M14:M14) -> 3250 | N15: =SUMPRODUCT($E$6:$E$6,N14:N14) -> 3165 | O15: =SUMPRODUCT($E$15:$E$15,O14:O14) -> 85 | P15: =SUMPRODUCT(E14,P14) -> 1800
A16: ***Please insert row before this line | G16: =G15+P16 -> 5730 | P16: 1800
E18: LBS | F18: =F15/0.46 -> 43.2

Sheet Margin Analysic (2)
A1: Job No. | B1: AC0481-DRT-OTHMY | E1: INQ DATE | G1: 46218 | K1: CURRENCY: | L1: USD
A2: Customer: | B2: Baker Huges | E2: Credit (days) | G2: 45 | H2: NET 60 DAYS | K2: USD->EUR: | L2: 1.1
A3: COUNTRY: | B3: MY | E3: Incoterm | H3: FCA | I3: LOUSIANA, US | K3: USD-->VND | L3: 25500
A4: Goods origin | B4: Oversea | H4: DDP | I4: Labuan | M4: Cost
A5: ITEM | B5: Part No. | C5: Description. | D5: Supplier | E5: Q'ty | F5: Weight (kg) | G5: Sales Price | H5: Total Revenue | I5: Margin per unit | J5: % Margin | K5: Total Margin | L5: Total Cost | M5: Unit Cost | N5: Material Cost | O5: Financial Cost
A6: 1 | B6: 480131200 | C6: 1R MODEL F STD. SERVICE DRILL PIPE FLOAT VALVE | D6: KEYSTONE | E6: 30 | F6: =(43.2/E6)*0.46 -> 0.6624 | G6: =ROUNDUP(M6/(1-J6),0) -> 131 | H6: =E6*G6 -> 3930 | I6: =G6-M6 -> 22.666667 | J6: 0.17 | K6: =E6*I6 -> 680 | L6: =M6*E6 -> 3250 | M6: =SUM(N6:O6) -> 108.33333 | N6: 105.5 | O6: =85*(N6/$N$7) -> 2.8333333
E7: =SUM(E6:E6) -> 30 | F7: =SUMPRODUCT($E$6:$E$6,F6:F6) -> 19.872 | G7: =SUMPRODUCT($E$6:$E$6,G6:G6) -> 3930 | H7: =SUM(H6:H6) -> 3930 | I7: =SUMPRODUCT($E$6:$E$6,I6:I6) -> 680 | J7: =AVERAGE(J6:J6) -> 0.17 | K7: =SUM(K6:K6) -> 680 | L7: =SUM(L6:L6) -> 3250 | M7: =SUMPRODUCT($E$6:$E$6,M6:M6) -> 3250 | N7: =SUMPRODUCT($E$6:$E$6,N6:N6) -> 3165 | O7: =SUMPRODUCT($E$6:$E$6,O6:O6) -> 85
A8: ***Please insert row before this line
F10: =F7/0.46 -> 43.2
B12: DAP Kemaman, Malaysia
A13: ITEM | B13: Part No. | C13: Description. | D13: Supplier | E13: Q'ty | F13: Weight (kg) | G13: Sales Price | H13: Total Revenue | I13: Margin per unit | J13: % Margin | K13: Total Margin | L13: Total Cost | M13: Unit Cost | N13: Material Cost | O13: Financial Cost | P13: Frieght
A14: 1 | B14: 480131200 | C14: 1R MODEL F STD. SERVICE DRILL PIPE FLOAT VALVE | D14: KEYSTONE | E14: 30 | F14: =(43.2/E14)*0.46 -> 0.6624 | G14: =ROUNDUP(M14/(1-J14),0) -> 133 | H14: =E14*G14 -> 3990 | I14: =G14-M14 -> 22.688542 | J14: 0.17 | K14: =E14*I14 -> 680.65625 | L14: =M14*E14 -> 3309.3438 | M14: =SUM(N14:O14) -> 110.31146 | N14: 105.5 | O14: =N14*(15%*45/360)+85*(N14/$N$15) -> 4.8114583 | P14: =(Logistic!G2*('Margin Analysic (2)'!F14/'Margin Analysic (2)'!F15)) -> 60
E15: =SUM(E14:E14) -> 30 | F15: =SUMPRODUCT($E$6:$E$6,F14:F14) -> 19.872 | G15: =SUMPRODUCT($E$6:$E$6,G14:G14) -> 3990 | H15: =SUM(H14:H14) -> 3990 | I15: =SUMPRODUCT($E$6:$E$6,I14:I14) -> 680.65625 | J15: =AVERAGE(J14:J14) -> 0.17 | K15: =SUM(K14:K14) -> 680.65625 | L15: =SUM(L14:L14) -> 3309.3438 | M15: =SUMPRODUCT($E$6:$E$6,M14:M14) -> 3309.3438 | N15: =SUMPRODUCT($E$6:$E$6,N14:N14) -> 3165 | O15: =SUMPRODUCT($E$15:$E$15,O14:O14) -> 144.34375 | P15: =SUMPRODUCT(E14,P14) -> 1800
A16: ***Please insert row before this line | G16: =G15+P16 -> 5090 | P16: 1100
E18: LBS | F18: =F15/0.46 -> 43.2
